pyglimmermds/__init__.py
pyglimmermds/glimmer.py
pyglimmermds/glimmer_alg.py
pyglimmermds/util.py
pyglimmermds-1.0.0.dist-info/licenses/LICENSE
pyglimmermds-1.0.0.dist-info/METADATA
pyglimmermds-1.0.0.dist-info/WHEEL
pyglimmermds-1.0.0.dist-info/top_level.txt
pyglimmermds-1.0.0.dist-info/RECORD
