Metadata-Version: 2.4
Name: PyGlimmerMDS
Version: 1.0.0
Summary: Python Implementation of the Glimmer algorithm for multidimensional scaling
Author: David Hägele
License: MIT License
Project-URL: Homepage, https://github.com/hageldave/PyGlimmerMDS
Project-URL: Bug Tracker, https://github.com/hageldave/PyGlimmerMDS/issues
Classifier: Programming Language :: Python :: 3
Classifier: License :: OSI Approved :: MIT License
Classifier: Operating System :: OS Independent
Requires-Python: >=3.10
License-File: LICENSE
Requires-Dist: numpy
Requires-Dist: numba
Dynamic: license-file
